CTkMessagebox/__init__.py
CTkMessagebox/ctkmessagebox.py
CTkMessagebox/icons/cancel.png
CTkMessagebox/icons/check.png
CTkMessagebox/icons/info.png
CTkMessagebox/icons/question.png
CTkMessagebox/icons/warning.png
CTkMessagebox-2.6.dist-info/LICENSE
CTkMessagebox-2.6.dist-info/METADATA
CTkMessagebox-2.6.dist-info/WHEEL
CTkMessagebox-2.6.dist-info/dependency_links.txt
CTkMessagebox-2.6.dist-info/top_level.txt
CTkMessagebox-2.6.dist-info/RECORD
