Metadata-Version: 2.1
Name: CTkMessagebox
Version: 2.6
Summary: A modern messagebox for customtkinter
Home-page: https://github.com/Akascape/CTkMessagebox
Author: Akash Bora
License: Creative Commons Zero v1.0 Universal
Keywords: customtkinter,customtkinter-dialog,customtkinter-messagebox,customtkinter-message-box,tkinter-messagebox,custom-messagebox,messagebox-widget,modern-tkinter-messagebox,ctkmessagebox,popup-window
Classifier: License :: CC0 1.0 Universal (CC0 1.0) Public Domain Dedication
Classifier: Programming Language :: Python :: 3
Classifier: Operating System :: OS Independent
Requires-Python: >=3.6
License-File: LICENSE
Requires-Dist: customtkinter
Requires-Dist: pillow
